asreview_makita-1.1.dist-info/licenses/LICENSE
asreviewcontrib/makita/__init__.py
asreviewcontrib/makita/_version.py
asreviewcontrib/makita/config.py
asreviewcontrib/makita/entrypoint.py
asreviewcontrib/makita/template_arfi.py
asreviewcontrib/makita/template_base.py
asreviewcontrib/makita/template_basic.py
asreviewcontrib/makita/template_modelmatrix.py
asreviewcontrib/makita/template_prior.py
asreviewcontrib/makita/utils.py
asreviewcontrib/makita/templates/doc_README.md.template
asreviewcontrib/makita/templates/script_data_describe.py.template
asreviewcontrib/makita/templates/script_get_plot.py.template
asreviewcontrib/makita/templates/script_get_settings_from_state.py.template
asreviewcontrib/makita/templates/script_merge_descriptives.py.template
asreviewcontrib/makita/templates/script_merge_metrics.py.template
asreviewcontrib/makita/templates/script_merge_tds.py.template
asreviewcontrib/makita/templates/script_split_data_with_multiple_labels.py.template
asreviewcontrib/makita/templates/template_arfi.txt.template
asreviewcontrib/makita/templates/template_basic.txt.template
asreviewcontrib/makita/templates/template_modelmatrix.txt.template
asreviewcontrib/makita/templates/template_prior.txt.template
asreview_makita-1.1.dist-info/METADATA
asreview_makita-1.1.dist-info/WHEEL
asreview_makita-1.1.dist-info/entry_points.txt
asreview_makita-1.1.dist-info/top_level.txt
asreview_makita-1.1.dist-info/RECORD
