Metadata-Version: 2.4
Name: asreview-makita
Version: 1.1
Summary: Makita workflow tool for the ASReview project
Author-email: ASReview LAB developers <asreview@uu.nl>
License: MIT
Project-URL: homepage, https://asreview.ai
Project-URL: repository, https://github.com/asreview/asreview-makita
Classifier: Development Status :: 4 - Beta
Classifier: License :: OSI Approved :: MIT License
Classifier: Programming Language :: Python :: 3.8
Classifier: Programming Language :: Python :: 3.9
Classifier: Programming Language :: Python :: 3.10
Classifier: Programming Language :: Python :: 3.11
Classifier: Programming Language :: Python :: 3.12
Requires-Python: >=3.10
License-File: LICENSE
Requires-Dist: asreview<3,>=2
Requires-Dist: jinja2
Requires-Dist: cfgtemplater
Provides-Extra: lint
Requires-Dist: ruff; extra == "lint"
Provides-Extra: test
Requires-Dist: pytest; extra == "test"
Dynamic: license-file
